intellimouse/__init__.py
intellimouse/classic_intellimouse.py
intellimouse/intellimouse.py
intellimouse/pro_intellimouse.py
intellimouse_ctl/__init__.py
intellimouse_ctl/__main__.py
intellimouse_ctl-1.0.0.dist-info/LICENSE
intellimouse_ctl-1.0.0.dist-info/METADATA
intellimouse_ctl-1.0.0.dist-info/WHEEL
intellimouse_ctl-1.0.0.dist-info/entry_points.txt
intellimouse_ctl-1.0.0.dist-info/top_level.txt
intellimouse_ctl-1.0.0.dist-info/RECORD
