Metadata-Version: 2.1
Name: intellimouse-ctl
Version: 1.0.0
Summary: A cross-platform command line tool and library for Microsofts IntelliMouse products.
Home-page: https://github.com/k-visscher/intellimouse-ctl
Author: Kim Visscher
Author-email: kim@visscher.codes
License: UNKNOWN
Project-URL: Bug Tracker, https://github.com/k-visscher/intellimouse-ctl/issues
Platform: UNKNOWN
Classifier: Programming Language :: Python :: 3.8
Classifier: Programming Language :: Python :: 3.9
Classifier: Programming Language :: Python :: 3.10
Classifier: License :: OSI Approved :: MIT License
Classifier: Operating System :: OS Independent
Requires-Python: >=3.8
License-File: LICENSE
Requires-Dist: hidapi (>=0.9.0.post3)
